{"nameInfos":{"1563860172":[{"instanceName":"SUN_CamAnim_THX_Tuyo","modelName":"SUN_CamAnim_THX","familyName":"cam_cine","numRules":2,"numReflexes":-1,"customBits":2}],"1560590742":[{"instanceName":"SUN_THX_Tuyo_Fin","modelName":"OLD_THX","familyName":"Gen_Cinematique","numRules":9,"numReflexes":-1,"customBits":270532608}],"1533432636":[{"instanceName":"StdCamer","modelName":"StdCam","familyName":"Camera","numRules":11,"numReflexes":1,"customBits":0}],"0":[{"instanceName":"global","modelName":"GlobalActorModel","familyName":"World","numRules":2,"numReflexes":-1,"customBits":135307264},{"instanceName":"World","modelName":"Leveljail_20","familyName":"World","numRules":3,"numReflexes":-1,"customBits":134217728},{"instanceName":"ARG_IconeGestionnaire_I1","modelName":"ARG_IconeGestionnaire","familyName":"icones","numRules":3,"numReflexes":-1,"customBits":40960}],"1529239961":[{"instanceName":"SUN_Glob_Cine_Intro","modelName":"SUN_Globox_Cinema","familyName":"Globox_Cine","numRules":3,"numReflexes":-1,"customBits":2097152}],"1535108713":[{"instanceName":"SUN_THX_Intro","modelName":"OLD_THX","familyName":"Gen_Cinematique","numRules":9,"numReflexes":-1,"customBits":404750336}],"1533018112":[{"instanceName":"SUN_Barriere_Laser_Cine_Intro","modelName":"SUN_Barriere_Laser_Cine","familyName":"faisceau","numRules":2,"numReflexes":-1,"customBits":2}],"1528543639":[{"instanceName":"SUN_Lums_Intro01","modelName":"SUN_Lums_Cinema","familyName":"Lums_Cine","numRules":2,"numReflexes":-1,"customBits":0}],"1560727559":[{"instanceName":"SUN_Glob_Cine_Tuyo","modelName":"SUN_Globox_Cinema","familyName":"Globox_Cine","numRules":3,"numReflexes":-1,"customBits":0}],"1535095605":[{"instanceName":"SUN_THX_BlaBla_Intro","modelName":"THX_BlaBla","familyName":"Gen_Cinematique","numRules":3,"numReflexes":1,"customBits":2097152},{"instanceName":"SUN_RayDummy_Intro_Jail","modelName":"SUN_RayDummy_Intro","familyName":"Ray_Intro","numRules":2,"numReflexes":-1,"customBits":2097152}],"1606334056":[{"instanceName":"SUN_RayDummy_Intro_Tuyo","modelName":"SUN_RayDummy_Intro","familyName":"Ray_Intro","numRules":2,"numReflexes":-1,"customBits":2097152}],"1540549290":[{"instanceName":"SUN_Lums_Tuyo_03","modelName":"Alw_Lums_Model","familyName":"Lums","numRules":6,"numReflexes":-1,"customBits":2101248}],"1534036650":[{"instanceName":"SUN_Lums_Tuyo_01","modelName":"Alw_Lums_Model","familyName":"Lums","numRules":6,"numReflexes":-1,"customBits":2101248}],"1535564184":[{"instanceName":"SUN_Lums_Tuyo_02","modelName":"Alw_Lums_Model","familyName":"Lums","numRules":6,"numReflexes":-1,"customBits":2101248}],"1512665918":[{"instanceName":"SUN_Lums_Tuyo_04","modelName":"Alw_Lums_Model","familyName":"Lums","numRules":6,"numReflexes":-1,"customBits":2101248}],"1533108220":[{"instanceName":"SUN_Grille_Cine_Intro","modelName":"SUN_Grille_Cine","familyName":"Ptite_grille","numRules":3,"numReflexes":-1,"customBits":2097186}],"1570031207":[{"instanceName":"SUN_Lums_Tuyo_05","modelName":"Alw_Lums_Model","familyName":"Lums","numRules":6,"numReflexes":-1,"customBits":2101248}],"678658040":[{"instanceName":"YAM_GenMenuMap_I1","modelName":"YAM_GenMenuMap","familyName":"Gen_YAM","numRules":23,"numReflexes":6,"customBits":1048576}],"1533176490":[{"instanceName":"SUN_PosCam_Cut_Tuyo","modelName":"SUN_PosCam_Cut","familyName":"GenCamera","numRules":4,"numReflexes":-1,"customBits":0}],"1568700827":[{"instanceName":"SUN_Lums_Tuyo_06","modelName":"Alw_Lums_Model","familyName":"Lums","numRules":6,"numReflexes":-1,"customBits":2101248}],"1567157451":[{"instanceName":"SUN_Lums_Tuyo_07","modelName":"Alw_Lums_Model","familyName":"Lums","numRules":6,"numReflexes":-1,"customBits":2101248}],"1567562137":[{"instanceName":"SUN_Lums_Tuyo_08","modelName":"Alw_Lums_Model","familyName":"Lums","numRules":6,"numReflexes":-1,"customBits":2101248}],"1535089048":[{"instanceName":"SUN_Cam_Oriente_I1","modelName":"SUN_Cam_Oriente","familyName":"GenCamera","numRules":4,"numReflexes":-1,"customBits":0}],"1530196789":[{"instanceName":"SUN_Sbire_Cine_Intro","modelName":"SUN_Sbire_Glob_Cine","familyName":"sbire_globox","numRules":2,"numReflexes":-1,"customBits":2097152}],"1533460478":[{"instanceName":"SUN_Helice_Start","modelName":"OLD_Helice01","familyName":"helice","numRules":2,"numReflexes":-1,"customBits":2}],"1539883006":[{"instanceName":"SUN_Helice_Fin","modelName":"OLD_Helice01","familyName":"helice","numRules":2,"numReflexes":-1,"customBits":2}],"1535082497":[{"instanceName":"Rayman","modelName":"YLT_RaymanModel","familyName":"rayman","numRules":46,"numReflexes":16,"customBits":2147483906}],"1383989248":[{"instanceName":"Alw_Projectile_Rayman","modelName":"Alw_Projectile_Rayman_Model","familyName":"projectiles","numRules":8,"numReflexes":-1,"customBits":131080}],"1383268352":[{"instanceName":"ALW_FaisceauGrappin","modelName":"FaisceauGrappin","familyName":"faisceau","numRules":-1,"numReflexes":-1,"customBits":2}],"1380450304":[{"instanceName":"ALW_TexteMenu","modelName":"CHG_TexteMenu","familyName":"alphabet","numRules":4,"numReflexes":-1,"customBits":1056770}],"1380777984":[{"instanceName":"ALW_FondMenu","modelName":"ARG_FondMenu","familyName":"menumap","numRules":1,"numReflexes":-1,"customBits":1048576}],"1380057088":[{"instanceName":"ALW_LumsCurseur","modelName":"YAM_LumsCurseur","familyName":"Lums","numRules":2,"numReflexes":1,"customBits":1048576}],"1380384768":[{"instanceName":"ALW_Plouf","modelName":"Alw_Plouf_Model","familyName":"flaque_plouf","numRules":5,"numReflexes":-1,"customBits":0}],"1381761024":[{"instanceName":"Alw_Fumee","modelName":"Alw_Fumee_model","familyName":"Nuage","numRules":3,"numReflexes":-1,"customBits":0}]},"centerX":366.517426,"centerY":229.248032,"centerZ":205.574646}